Shifter/enabler.v
// hold enabled output high for fixed number of clock cycles

module enabler( clk, enabled, enable, reset, initial_count );
	parameter width = 8;

	output enabled;
	input clk, enable, reset;
	input [ width - 1 : 0] initial_count;

	reg [ width - 1 : 0 ] count;

	always @( posedge clk or posedge reset )
	begin
		if( reset )
			begin
				count <= initial_count;
			end
		else if( enable && count > 0 )
			begin
				count <= count - 1;
			end
		// no change if not load or enable
	end

	assign enabled = enable && ( count > 0 );

endmodule

Shifter/shift_in.v
// shift register, serial in, parallel out, async clear

module shift_in( clk, clr, enable, si, dout, done );
	parameter width = 32;

	input clk, si, clr, enable;
	output [ width - 1 : 0 ] dout;
	output done;

	reg [ width : 0 ] data;

	always @( posedge clk or posedge clr )
	begin
		if( clr )
			data <= 1; // { ( width ){ 1'b0 }};
		else if( enable && !done )
			data <= { data[ width - 1 : 0 ], si };
		// no changeif not clear or enable
	end

	assign dout = { data[ width - 1 : 0 ] };
	assign done = data[ width ];
endmodule

Shifter/shift_out.v
// shift register, parallel in, serial out

module shift_out( input clk, load, enable, input [ width - 1 : 0 ] init_value, output sout );
	parameter width = 32;
	parameter cwidth = 5;

	reg [ width - 1 : 0 ] data;
	reg [ cwidth - 1 : 0 ] index;
	reg done;

	always @( posedge clk or posedge load )
	begin
		if( load )
			begin
				data <= init_value;
				index <= 0;
				done <= 0;
			end
		else if( enable && !done )
			begin
				index <= index +1;
				done <= &index;
			end
		// no change if not load or enable
	end

	assign sout = data[ index ];

endmodule

Shifter/shifter_test.v
`define WIDTH 8

`include "shift_in.v"
`include "shift_out.v"
`include "enabler.v"

//Test bench connects the flip-flop to the tester module
module testbench;
    initial begin
		initial_count = 12;
        //Dump results of the simulation to file
        $dumpfile( "shifter_test.vcd" );
        $dumpvars;
	end

	defparam writer.width = `WIDTH;
	defparam writer.cwidth = 3;
	defparam reader.width = `WIDTH;

    wire clk, load, clr, enable, sio;
	wire	[ `WIDTH - 1 : 0 ] data_in;
	wire	[ `WIDTH - 1 : 0 ] data_out;
	reg [7:0] initial_count;
	wire enabled;

	shift_out writer( clk, load, enable, data_in, sio );
	shift_in reader( clk, clr, enable, sio, data_out, done );
	enabler enabler1( clk, enabled, enable, load, initial_count );

    tester test1( data_in, clk, load, clr, enable );
endmodule

//Tester module sends a periodic clock signal to the DUT
module tester( data_in, clk, load, clr, enable );
    output [ `WIDTH - 1 : 0 ] data_in;
    // output [ `WIDTH - 1 : 0 ] data_out;
	output clk, load, clr, enable;
    reg clk, load, clr, enable;
	reg [ `WIDTH - 1 : 0 ] data_in;
	// reg [ `WIDTH - 1 : 0 ] data_out;

    //Generate periodic clock signal
    always
    begin
        #1 clk=!clk;
    end

    initial
    begin
		// initial conditions
        clk=0;
        clr = 0;
        load=0;
        enable=0;
		data_in = 8'b11000011;
		// data_out = 8'b00000000;

        //Generate stimulus signals
		#2	load = 1;
				clr = 1;

		#2	load = 0;
				clr = 0;

		#2	enable = 1;

		#24	enable = 0;

        #4 $finish;
    end
endmodule

Shifter/shifter_test.vcd
$date
	Sun Sep 29 22:45:28 2013
$end
$version
	Icarus Verilog
$end
$timescale
	1s
$end
$scope module testbench $end
$var wire 1 ! clk $end
$var wire 1 " clr $end
$var wire 8 # data_in [7:0] $end
$var wire 8 $ data_out [7:0] $end
$var wire 1 % done $end
$var wire 1 & enable $end
$var wire 1 ' enabled $end
$var wire 1 ( load $end
$var wire 1 ) sio $end
$var reg 8 * initial_count [7:0] $end
$scope module writer $end
$var wire 1 ! clk $end
$var wire 1 & enable $end
$var wire 8 + init_value [7:0] $end
$var wire 1 ( load $end
$var wire 1 ) sout $end
$var reg 8 , data [7:0] $end
$var reg 1 - done $end
$var reg 3 . index [2:0] $end
$upscope $end
$scope module reader $end
$var wire 1 ! clk $end
$var wire 1 " clr $end
$var wire 1 % done $end
$var wire 8 / dout [7:0] $end
$var wire 1 & enable $end
$var wire 1 ) si $end
$var reg 9 0 data [8:0] $end
$upscope $end
$scope module enabler1 $end
$var wire 1 ! clk $end
$var wire 1 & enable $end
$var wire 1 ' enabled $end
$var wire 8 1 initial_count [7:0] $end
$var wire 1 ( reset $end
$var reg 8 2 count [7:0] $end
$upscope $end
$scope module test1 $end
$var reg 1 3 clk $end
$var reg 1 4 clr $end
$var reg 8 5 data_in [7:0] $end
$var reg 1 6 enable $end
$var reg 1 7 load $end
$upscope $end
$upscope $end
$enddefinitions $end
#0
$dumpvars
07
06
b11000011 5
04
03
bx 2
b1100 1
bx 0
bx /
bx .
x-
bx ,
b11000011 +
b1100 *
x)
0(
0'
0&
x%
bx $
b11000011 #
0"
0!
$end
#1
13
1!
#2
b1 $
b1 /
0%
b1 0
b1100 2
0-
b0 .
1)
b11000011 ,
03
0!
14
1"
17
1(
#3
13
1!
#4
03
0!
04
0"
07
0(
#5
13
1!
#6
1'
03
0!
16
1&
#7
b11 $
b11 /
b1 .
b1011 2
b11 0
13
1!
#8
03
0!
#9
b111 $
b111 /
b1010 2
b10 .
0)
b111 0
13
1!
#10
03
0!
#11
b1110 $
b1110 /
b11 .
b1001 2
b1110 0
13
1!
#12
03
0!
#13
b11100 $
b11100 /
b1000 2
b100 .
b11100 0
13
1!
#14
03
0!
#15
b111000 $
b111000 /
b101 .
b111 2
b111000 0
13
1!
#16
03
0!
#17
b1110000 $
b1110000 /
b110 2
b110 .
1)
b1110000 0
13
1!
#18
03
0!
#19
b11100001 $
b11100001 /
b111 .
b101 2
b11100001 0
13
1!
#20
03
0!
#21
b11000011 $
b11000011 /
1%
b100 2
1-
b0 .
b111000011 0
13
1!
#22
03
0!
#23
b11 2
13
1!
#24
03
0!
#25
b10 2
13
1!
#26
03
0!
#27
b1 2
13
1!
#28
03
0!
#29
0'
b0 2
13
1!
#30
03
0!
06
0&
